{
  "collapse-filter": false,
  "search": "tag:#bvi",
  "showTags": true,
  "showAttachments": false,
  "hideUnresolved": false,
  "showOrphans": true,
  "collapse-color-groups": false,
  "colorGroups": [
    {
      "query": "tag:iran",
      "color": {
        "a": 1,
        "rgb": 14701138
      }
    },
    {
      "query": "tag:dprk",
      "color": {
        "a": 1,
        "rgb": 14725458
      }
    },
    {
      "query": "tag:china",
      "color": {
        "a": 1,
        "rgb": 11657298
      }
    },
    {
      "query": "tag:russia",
      "color": {
        "a": 1,
        "rgb": 5431378
      }
    },
    {
      "query": "tag:pakistan",
      "color": {
        "a": 1,
        "rgb": 5431473
      }
    },
    {
      "query": "tag:hawala",
      "color": {
        "a": 1,
        "rgb": 5419488
      }
    }
  ],
  "collapse-display": true,
  "showArrow": false,
  "textFadeMultiplier": 0,
  "nodeSizeMultiplier": 1,
  "lineSizeMultiplier": 1,
  "collapse-forces": false,
  "centerStrength": 0.508316008316008,
  "repelStrength": 6.67359667359667,
  "linkStrength": 1,
  "linkDistance": 148,
  "scale": 1,
  "close": false
}